<?xml version="1.0" encoding="UTF-8"?>
<!DOCTYPE mapper PUBLIC "-//mybatis.org//DTD Mapper 3.0//EN" "http://mybatis.org/dtd/mybatis-3-mapper.dtd">
<mapper namespace="it.csi.serse.serseweb.integration.mybatis.generated.dao.SerseDLivelloIstruzioneDAO">
  <resultMap id="BaseResultMap" type="it.csi.serse.serseweb.integration.mybatis.generated.dto.SerseDLivelloIstruzioneDTO">
    <!--
      WARNING - @mbg.generated
      This element is automatically generated by MyBatis Generator, do not modify.
      This element was generated on Wed Oct 18 12:27:46 CEST 2023.
    -->
    <id column="cod_livello_istruzione" jdbcType="VARCHAR" property="codLivelloIstruzione" />
    <result column="descr_livello_istruzione" jdbcType="VARCHAR" property="descrLivelloIstruzione" />
    <result column="d_inizio" jdbcType="TIMESTAMP" property="dInizio" />
    <result column="d_fine" jdbcType="CHAR" property="dFine" />
  </resultMap>
  <sql id="Example_Where_Clause">
    <!--
      WARNING - @mbg.generated
      This element is automatically generated by MyBatis Generator, do not modify.
      This element was generated on Wed Oct 18 12:27:46 CEST 2023.
    -->
    <where>
      <foreach collection="oredCriteria" item="criteria" separator="or">
        <if test="criteria.valid">
          <trim prefix="(" prefixOverrides="and" suffix=")">
            <foreach collection="criteria.criteria" item="criterion">
              <choose>
                <when test="criterion.noValue">
                  and ${criterion.condition}
                </when>
                <when test="criterion.singleValue">
                  and ${criterion.condition} #{criterion.value}
                </when>
                <when test="criterion.betweenValue">
                  and ${criterion.condition} #{criterion.value} and #{criterion.secondValue}
                </when>
                <when test="criterion.listValue">
                  and ${criterion.condition}
                  <foreach close=")" collection="criterion.value" item="listItem" open="(" separator=",">
                    #{listItem}
                  </foreach>
                </when>
              </choose>
            </foreach>
          </trim>
        </if>
      </foreach>
    </where>
  </sql>
  <sql id="Update_By_Example_Where_Clause">
    <!--
      WARNING - @mbg.generated
      This element is automatically generated by MyBatis Generator, do not modify.
      This element was generated on Wed Oct 18 12:27:46 CEST 2023.
    -->
    <where>
      <foreach collection="example.oredCriteria" item="criteria" separator="or">
        <if test="criteria.valid">
          <trim prefix="(" prefixOverrides="and" suffix=")">
            <foreach collection="criteria.criteria" item="criterion">
              <choose>
                <when test="criterion.noValue">
                  and ${criterion.condition}
                </when>
                <when test="criterion.singleValue">
                  and ${criterion.condition} #{criterion.value}
                </when>
                <when test="criterion.betweenValue">
                  and ${criterion.condition} #{criterion.value} and #{criterion.secondValue}
                </when>
                <when test="criterion.listValue">
                  and ${criterion.condition}
                  <foreach close=")" collection="criterion.value" item="listItem" open="(" separator=",">
                    #{listItem}
                  </foreach>
                </when>
              </choose>
            </foreach>
          </trim>
        </if>
      </foreach>
    </where>
  </sql>
  <sql id="Base_Column_List">
    <!--
      WARNING - @mbg.generated
      This element is automatically generated by MyBatis Generator, do not modify.
      This element was generated on Wed Oct 18 12:27:46 CEST 2023.
    -->
    cod_livello_istruzione, descr_livello_istruzione, d_inizio, d_fine
  </sql>
  <select id="selectByExample" parameterType="it.csi.serse.serseweb.integration.mybatis.generated.dto.SerseDLivelloIstruzioneSelector" resultMap="BaseResultMap">
    <!--
      WARNING - @mbg.generated
      This element is automatically generated by MyBatis Generator, do not modify.
      This element was generated on Wed Oct 18 12:27:46 CEST 2023.
    -->
    select
    <if test="distinct">
      distinct
    </if>
    <include refid="Base_Column_List" />
    from serse_d_livello_istruzione
    <if test="_parameter != null">
      <include refid="Example_Where_Clause" />
    </if>
    <if test="orderByClause != null">
      order by ${orderByClause}
    </if>
  </select>
  <select id="selectByPrimaryKey" parameterType="java.lang.String" resultMap="BaseResultMap">
    <!--
      WARNING - @mbg.generated
      This element is automatically generated by MyBatis Generator, do not modify.
      This element was generated on Wed Oct 18 12:27:46 CEST 2023.
    -->
    select 
    <include refid="Base_Column_List" />
    from serse_d_livello_istruzione
    where cod_livello_istruzione = #{codLivelloIstruzione,jdbcType=VARCHAR}
  </select>
  <delete id="deleteByPrimaryKey" parameterType="java.lang.String">
    <!--
      WARNING - @mbg.generated
      This element is automatically generated by MyBatis Generator, do not modify.
      This element was generated on Wed Oct 18 12:27:46 CEST 2023.
    -->
    delete from serse_d_livello_istruzione
    where cod_livello_istruzione = #{codLivelloIstruzione,jdbcType=VARCHAR}
  </delete>
  <delete id="deleteByExample" parameterType="it.csi.serse.serseweb.integration.mybatis.generated.dto.SerseDLivelloIstruzioneSelector">
    <!--
      WARNING - @mbg.generated
      This element is automatically generated by MyBatis Generator, do not modify.
      This element was generated on Wed Oct 18 12:27:46 CEST 2023.
    -->
    delete from serse_d_livello_istruzione
    <if test="_parameter != null">
      <include refid="Example_Where_Clause" />
    </if>
  </delete>
  <insert id="insert" parameterType="it.csi.serse.serseweb.integration.mybatis.generated.dto.SerseDLivelloIstruzioneDTO">
    <!--
      WARNING - @mbg.generated
      This element is automatically generated by MyBatis Generator, do not modify.
      This element was generated on Wed Oct 18 12:27:46 CEST 2023.
    -->
    insert into serse_d_livello_istruzione (cod_livello_istruzione, descr_livello_istruzione, 
      d_inizio, d_fine)
    values (#{codLivelloIstruzione,jdbcType=VARCHAR}, #{descrLivelloIstruzione,jdbcType=VARCHAR}, 
      #{dInizio,jdbcType=TIMESTAMP}, #{dFine,jdbcType=CHAR})
  </insert>
  <insert id="insertSelective" parameterType="it.csi.serse.serseweb.integration.mybatis.generated.dto.SerseDLivelloIstruzioneDTO">
    <!--
      WARNING - @mbg.generated
      This element is automatically generated by MyBatis Generator, do not modify.
      This element was generated on Wed Oct 18 12:27:46 CEST 2023.
    -->
    insert into serse_d_livello_istruzione
    <trim prefix="(" suffix=")" suffixOverrides=",">
      <if test="codLivelloIstruzione != null">
        cod_livello_istruzione,
      </if>
      <if test="descrLivelloIstruzione != null">
        descr_livello_istruzione,
      </if>
      <if test="dInizio != null">
        d_inizio,
      </if>
      <if test="dFine != null">
        d_fine,
      </if>
    </trim>
    <trim prefix="values (" suffix=")" suffixOverrides=",">
      <if test="codLivelloIstruzione != null">
        #{codLivelloIstruzione,jdbcType=VARCHAR},
      </if>
      <if test="descrLivelloIstruzione != null">
        #{descrLivelloIstruzione,jdbcType=VARCHAR},
      </if>
      <if test="dInizio != null">
        #{dInizio,jdbcType=TIMESTAMP},
      </if>
      <if test="dFine != null">
        #{dFine,jdbcType=CHAR},
      </if>
    </trim>
  </insert>
  <select id="countByExample" parameterType="it.csi.serse.serseweb.integration.mybatis.generated.dto.SerseDLivelloIstruzioneSelector" resultType="java.lang.Long">
    <!--
      WARNING - @mbg.generated
      This element is automatically generated by MyBatis Generator, do not modify.
      This element was generated on Wed Oct 18 12:27:46 CEST 2023.
    -->
    select count(*) from serse_d_livello_istruzione
    <if test="_parameter != null">
      <include refid="Example_Where_Clause" />
    </if>
  </select>
  <update id="updateByExampleSelective" parameterType="map">
    <!--
      WARNING - @mbg.generated
      This element is automatically generated by MyBatis Generator, do not modify.
      This element was generated on Wed Oct 18 12:27:46 CEST 2023.
    -->
    update serse_d_livello_istruzione
    <set>
      <if test="record.codLivelloIstruzione != null">
        cod_livello_istruzione = #{record.codLivelloIstruzione,jdbcType=VARCHAR},
      </if>
      <if test="record.descrLivelloIstruzione != null">
        descr_livello_istruzione = #{record.descrLivelloIstruzione,jdbcType=VARCHAR},
      </if>
      <if test="record.dInizio != null">
        d_inizio = #{record.dInizio,jdbcType=TIMESTAMP},
      </if>
      <if test="record.dFine != null">
        d_fine = #{record.dFine,jdbcType=CHAR},
      </if>
    </set>
    <if test="_parameter != null">
      <include refid="Update_By_Example_Where_Clause" />
    </if>
  </update>
  <update id="updateByExample" parameterType="map">
    <!--
      WARNING - @mbg.generated
      This element is automatically generated by MyBatis Generator, do not modify.
      This element was generated on Wed Oct 18 12:27:46 CEST 2023.
    -->
    update serse_d_livello_istruzione
    set cod_livello_istruzione = #{record.codLivelloIstruzione,jdbcType=VARCHAR},
      descr_livello_istruzione = #{record.descrLivelloIstruzione,jdbcType=VARCHAR},
      d_inizio = #{record.dInizio,jdbcType=TIMESTAMP},
      d_fine = #{record.dFine,jdbcType=CHAR}
    <if test="_parameter != null">
      <include refid="Update_By_Example_Where_Clause" />
    </if>
  </update>
  <update id="updateByPrimaryKeySelective" parameterType="it.csi.serse.serseweb.integration.mybatis.generated.dto.SerseDLivelloIstruzioneDTO">
    <!--
      WARNING - @mbg.generated
      This element is automatically generated by MyBatis Generator, do not modify.
      This element was generated on Wed Oct 18 12:27:46 CEST 2023.
    -->
    update serse_d_livello_istruzione
    <set>
      <if test="descrLivelloIstruzione != null">
        descr_livello_istruzione = #{descrLivelloIstruzione,jdbcType=VARCHAR},
      </if>
      <if test="dInizio != null">
        d_inizio = #{dInizio,jdbcType=TIMESTAMP},
      </if>
      <if test="dFine != null">
        d_fine = #{dFine,jdbcType=CHAR},
      </if>
    </set>
    where cod_livello_istruzione = #{codLivelloIstruzione,jdbcType=VARCHAR}
  </update>
  <update id="updateByPrimaryKey" parameterType="it.csi.serse.serseweb.integration.mybatis.generated.dto.SerseDLivelloIstruzioneDTO">
    <!--
      WARNING - @mbg.generated
      This element is automatically generated by MyBatis Generator, do not modify.
      This element was generated on Wed Oct 18 12:27:46 CEST 2023.
    -->
    update serse_d_livello_istruzione
    set descr_livello_istruzione = #{descrLivelloIstruzione,jdbcType=VARCHAR},
      d_inizio = #{dInizio,jdbcType=TIMESTAMP},
      d_fine = #{dFine,jdbcType=CHAR}
    where cod_livello_istruzione = #{codLivelloIstruzione,jdbcType=VARCHAR}
  </update>
</mapper>